README.rst
setup.cfg
setup.py
json_url_rewriter/__init__.py
json_url_rewriter/config.py
json_url_rewriter/middleware.py
json_url_rewriter/rewrite.py
json_url_rewriter.egg-info/PKG-INFO
json_url_rewriter.egg-info/SOURCES.txt
json_url_rewriter.egg-info/dependency_links.txt
json_url_rewriter.egg-info/not-zip-safe
json_url_rewriter.egg-info/top_level.txt