Metadata-Version: 1.1
Name: json-url-rewriter
Version: 0.1.1
Summary: Helpers for rewriting links in JSON.
Home-page: https://github.com/ionrock/json_url_rewriter
Author: Eric Larson
Author-email: eric@ionrock.org
License: BSD
Keywords: json_url_rewriter
Platform: UNKNOWN
Classifier: Development Status :: 2 - Pre-Alpha
Classifier: Intended Audience :: Developers
Classifier: License :: OSI Approved :: BSD License
Classifier: Natural Language :: English
Classifier: Programming Language :: Python :: 2
Classifier: Programming Language :: Python :: 2.6
Classifier: Programming Language :: Python :: 2.7
Classifier: Programming Language :: Python :: 3
Classifier: Programming Language :: Python :: 3.3
Classifier: Programming Language :: Python :: 3.4
